awslabs/well_architected_security_mcp_server/__init__.py
awslabs/well_architected_security_mcp_server/consts.py
awslabs/well_architected_security_mcp_server/server.py
awslabs/well_architected_security_mcp_server/util/__init__.py
awslabs/well_architected_security_mcp_server/util/network_security.py
awslabs/well_architected_security_mcp_server/util/prompt_utils.py
awslabs/well_architected_security_mcp_server/util/resource_utils.py
awslabs/well_architected_security_mcp_server/util/security_services.py
awslabs/well_architected_security_mcp_server/util/storage_security.py
awslabs_well_architected_security_mcp_server-0.1.5.dist-info/METADATA
awslabs_well_architected_security_mcp_server-0.1.5.dist-info/WHEEL
awslabs_well_architected_security_mcp_server-0.1.5.dist-info/entry_points.txt
awslabs_well_architected_security_mcp_server-0.1.5.dist-info/RECORD
