Metadata-Version: 2.4
Name: awslabs.well-architected-security-mcp-server
Version: 0.1.5
Summary: AWS Well-Architected Security Assessment Tool MCP Server
Requires-Python: >=3.10
Requires-Dist: boto3>=1.28.0
Requires-Dist: fastapi>=0.100.0
Requires-Dist: loguru>=0.7.0
Requires-Dist: mcp[cli]>=1.23.0
Requires-Dist: pydantic>=2.0.0
Requires-Dist: pyright>=1.1.0
Requires-Dist: pytest-asyncio>=0.26.0
Requires-Dist: pytest-cov>=4.1.0
Requires-Dist: pytest-mock>=3.12.0
Requires-Dist: pytest>=7.0.0
Requires-Dist: ruff>=0.0.291
